Xbyte_Common_Scrape/__init__.py
Xbyte_Common_Scrape/mymodules.py
mymodules-7.0.6.dist-info/METADATA
mymodules-7.0.6.dist-info/WHEEL
mymodules-7.0.6.dist-info/top_level.txt
mymodules-7.0.6.dist-info/RECORD
