Metadata-Version: 2.1
Name: mymodules
Version: 7.0.6
Summary: Simple helping tool for scraping
Author: XBYTE
Author-email: <mail@neuralnine.com>
Keywords: json,pymysql,requests,random_user_agent
Classifier: Development Status :: 1 - Planning
Classifier: Intended Audience :: Developers
Classifier: Programming Language :: Python :: 3
Classifier: Operating System :: Unix
Classifier: Operating System :: MacOS :: MacOS X
Classifier: Operating System :: Microsoft :: Windows
